hwo_sci_eng/json/Telescope-EAC1.json
hwo_sci_eng/json/Telescope-EAC2.json
hwo_sci_eng/json/Telescope-EAC3.json
hwo_sci_eng/json/WFI.json
hwo_sci_eng/json/__init__.py
hwo_sci_eng/obs_config/__init__.py
hwo_sci_eng/obs_config/CI/CI.yaml
hwo_sci_eng/obs_config/CI/IRFusedSilica_trans.yaml
hwo_sci_eng/obs_config/Detectors/RST_H4RG_Mean_QE.yaml
hwo_sci_eng/obs_config/Detectors/SaphiraLMAPDwGain_QE.yaml
hwo_sci_eng/obs_config/Detectors/Teledyne_COSMOS_CMOS_QE.yaml
hwo_sci_eng/obs_config/Detectors/Teledyne_e2v_EMCCD_QE.yaml
hwo_sci_eng/obs_config/HRI/HRI.yaml
hwo_sci_eng/obs_config/Tel/EAC1.yaml
hwo_sci_eng/obs_config/Tel/EAC2_draft.yaml
hwo_sci_eng/obs_config/Tel/EAC3_draft.yaml
hwo_sci_eng/obs_config/Tel/ProtectedAg_refl.yaml
hwo_sci_eng/obs_config/Tel/ProtectedAl_refl.yaml
hwo_sci_eng/obs_config/Tel/XeLiF_refl.yaml
hwo_sci_eng/obs_config/UVI/FUV_filter_trans.yaml
hwo_sci_eng/obs_config/UVI/MCP_QE.yaml
hwo_sci_eng/obs_config/UVI/UVFusedSilica_trans.yaml
hwo_sci_eng/obs_config/UVI/UVI.yaml
hwo_sci_eng/obs_config/UVI/cross_disperser_grating_efficiency.yaml
hwo_sci_eng/obs_config/UVI/echelle_grating_efficiency.yaml
hwo_sci_eng/test/test.py
hwo_sci_eng/utils/__init__.py
hwo_sci_eng/utils/read_json.py
hwo_sci_eng/utils/read_yaml.py
hwo_sci_eng-0.1.8.dist-info/LICENSE
hwo_sci_eng-0.1.8.dist-info/METADATA
hwo_sci_eng-0.1.8.dist-info/WHEEL
hwo_sci_eng-0.1.8.dist-info/top_level.txt
hwo_sci_eng-0.1.8.dist-info/RECORD
